common/__init__.py
common/decorators.py
common/descriptors.py
common/errors.py
common/metaclasses.py
common/utils.py
common/variables.py
logs/__init__.py
logs/config_server_log.py
server/__init__.py
server/add_user.py
server/config_window.py
server/core.py
server/database.py
server/main_window.py
server/remove_user.py
server/stat_window.py
unit_tests/__init__.py
nix86_mess_server-0.1.0.dist-info/METADATA
nix86_mess_server-0.1.0.dist-info/WHEEL
nix86_mess_server-0.1.0.dist-info/top_level.txt
nix86_mess_server-0.1.0.dist-info/RECORD
